ANFISpy/__init__.py
ANFISpy/anfis.py
ANFISpy/layers.py
ANFISpy/mfs.py
ANFISpy/tnorms.py
ANFISpy/utils.py
anfispy-1.2.1.dist-info/licenses/LICENSE
anfispy-1.2.1.dist-info/METADATA
anfispy-1.2.1.dist-info/WHEEL
anfispy-1.2.1.dist-info/top_level.txt
anfispy-1.2.1.dist-info/RECORD
