Metadata-Version: 2.4
Name: anfispy
Version: 1.2.1
Home-page: https://github.com/mZaiam/ANFISpy
Author: Matheus Zaia Monteiro
Author-email: matheus.z.monteiro@gmail.com
Requires-Python: >=3.10.8
License-File: LICENSE
Requires-Dist: torch>=2.5.1
Requires-Dist: numpy>=2.1.3
Requires-Dist: matplotlib>=3.10.0
Dynamic: author
Dynamic: author-email
Dynamic: home-page
Dynamic: license-file
Dynamic: requires-dist
Dynamic: requires-python
